[
  {
    "name": "rur",
    "value": "\"NCG\\05456365519969\\0541783505336:01fef65112b59e8ff70f1193219404df25a9f69da6bb1e438ffff01b972b97bf91be1c37\"",
    "domain": ".instagram.com",
    "path": "/",
    "expires": -1,
    "size": 110,
    "httpOnly": true,
    "secure": true,
    "session": true,
    "sameSite": "Lax",
    "priority": "Medium",
    "sameParty": false,
    "sourceScheme": "Secure"
  },
  {
    "name": "ds_user_id",
    "value": "56365519969",
    "domain": ".instagram.com",
    "path": "/",
    "expires": 1759745336.703533,
    "size": 21,
    "httpOnly": false,
    "secure": true,
    "session": false,
    "sameSite": "None",
    "priority": "Medium",
    "sameParty": false,
    "sourceScheme": "Secure"
  },
  {
    "name": "csrftoken",
    "value": "t7xozDh8iiLBZUdx6D1Ixf4YxaKJmt1F",
    "domain": ".instagram.com",
    "path": "/",
    "expires": 1786529336.703416,
    "size": 41,
    "httpOnly": false,
    "secure": true,
    "session": false,
    "priority": "Medium",
    "sameParty": false,
    "sourceScheme": "Secure"
  },
  {
    "name": "ig_nrcb",
    "value": "1",
    "domain": ".instagram.com",
    "path": "/",
    "expires": 1783505312.081144,
    "size": 8,
    "httpOnly": false,
    "secure": true,
    "session": false,
    "priority": "Medium",
    "sameParty": false,
    "sourceScheme": "Secure"
  },
  {
    "name": "sessionid",
    "value": "56365519969%3AF8rotFvKbguRww%3A22%3AAYcHx--AnUYMEriYynQL8T4H9Y7-L02n0TPEqc4Jkg",
    "domain": ".instagram.com",
    "path": "/",
    "expires": 1783505333.304854,
    "size": 87,
    "httpOnly": true,
    "secure": true,
    "session": false,
    "priority": "Medium",
    "sameParty": false,
    "sourceScheme": "Secure"
  },
  {
    "name": "dpr",
    "value": "1",
    "domain": ".instagram.com",
    "path": "/",
    "expires": 1752574136,
    "size": 4,
    "httpOnly": false,
    "secure": true,
    "session": false,
    "sameSite": "None",
    "priority": "Medium",
    "sameParty": false,
    "sourceScheme": "Secure"
  },
  {
    "name": "mid",
    "value": "aGzuGgAAAAEFYff_UZxSGBhm5ID7",
    "domain": ".instagram.com",
    "path": "/",
    "expires": 1786529308,
    "size": 31,
    "httpOnly": false,
    "secure": true,
    "session": false,
    "priority": "Medium",
    "sameParty": false,
    "sourceScheme": "Secure"
  },
  {
    "name": "wd",
    "value": "800x600",
    "domain": ".instagram.com",
    "path": "/",
    "expires": 1752574136,
    "size": 9,
    "httpOnly": false,
    "secure": true,
    "session": false,
    "sameSite": "None",
    "priority": "Medium",
    "sameParty": false,
    "sourceScheme": "Secure"
  },
  {
    "name": "ig_did",
    "value": "7B6D96FC-D9D8-4F29-B29C-52F16EBAFE25",
    "domain": ".instagram.com",
    "path": "/",
    "expires": 1783505306.768978,
    "size": 42,
    "httpOnly": true,
    "secure": true,
    "session": false,
    "priority": "Medium",
    "sameParty": false,
    "sourceScheme": "Secure"
  },
  {
    "name": "datr",
    "value": "Gu5saIHDd7Z21P7SD0WYybhR",
    "domain": ".instagram.com",
    "path": "/",
    "expires": 1786529306.768959,
    "size": 28,
    "httpOnly": true,
    "secure": true,
    "session": false,
    "priority": "Medium",
    "sameParty": false,
    "sourceScheme": "Secure"
  }
]